aws_excom/__init__.py
aws_excom/aws.py
aws_excom/cli.py
aws_excom/exceptions.py
aws_excom/tests/__init__.py
aws_excom/tests/test_aws.py
aws_excom/tests/test_install.py
aws_excom-0.0.20.dist-info/LICENSE
aws_excom-0.0.20.dist-info/METADATA
aws_excom-0.0.20.dist-info/WHEEL
aws_excom-0.0.20.dist-info/entry_points.txt
aws_excom-0.0.20.dist-info/top_level.txt
aws_excom-0.0.20.dist-info/RECORD
