Metadata-Version: 2.1
Name: aws-excom
Version: 0.0.20
Summary: Wrapper for AWS ECS Execute Command
Author-email: Ben Vosper <author@example.com>
Project-URL: Homepage, https://github.com/benvosper/aws-excom/
Project-URL: Bug Tracker, https://github.com/pypa/aws-excom/issues/
Classifier: Programming Language :: Python :: 3
Classifier: License :: OSI Approved :: MIT License
Classifier: Operating System :: OS Independent
Requires-Python: >=3.7
License-File: LICENSE
Requires-Dist: simple-term-menu
Requires-Dist: termcolor
Requires-Dist: boto3 (>=1.26)
Provides-Extra: deploy
Requires-Dist: build ; extra == 'deploy'
Requires-Dist: twine ; extra == 'deploy'
Provides-Extra: dev
Requires-Dist: pytest ; extra == 'dev'
Requires-Dist: pytest-virtualenv ; extra == 'dev'
Requires-Dist: black ; extra == 'dev'
Requires-Dist: moto ; extra == 'dev'
